qmdesc/QM_137k.pt
qmdesc/__init__.py
qmdesc/featurization.py
qmdesc/ffn.py
qmdesc/handler.py
qmdesc/model.py
qmdesc/mpn.py
qmdesc/nn_utils.py
qmdesc-1.0.6.dist-info/LICENSE
qmdesc-1.0.6.dist-info/METADATA
qmdesc-1.0.6.dist-info/WHEEL
qmdesc-1.0.6.dist-info/entry_points.txt
qmdesc-1.0.6.dist-info/top_level.txt
qmdesc-1.0.6.dist-info/RECORD
