Metadata-Version: 2.1
Name: qmdesc
Version: 1.0.6
Summary: A qm descriptor prediction package
Home-page: https://github.com/yanfeiguan/qmdesc
Author: Yanfei Guan
Author-email: yanfeig@mit.edu
License: MIT
Keywords: chemistry,machine learning,QM descriptors
Platform: UNKNOWN
Classifier: Programming Language :: Python :: 3
Classifier: License :: OSI Approved :: MIT License
Classifier: Operating System :: OS Independent
Requires-Python: >=3.6
Requires-Dist: torch (>=1.4.0)
Requires-Dist: numpy (>=1.18.1)
